coinzo/__init__.py
coinzo/api.py
coinzo/exceptions.py
coinzo/websockets.py
python_coinzo-0.1.5.dist-info/LICENSE
python_coinzo-0.1.5.dist-info/METADATA
python_coinzo-0.1.5.dist-info/WHEEL
python_coinzo-0.1.5.dist-info/top_level.txt
python_coinzo-0.1.5.dist-info/RECORD
