Metadata-Version: 2.1
Name: python-coinzo
Version: 0.1.5
Summary: coinzo REST API python implementation
Home-page: https://github.com/tolgamorf/python-coinzo
Author: tolgamorf
Author-email: cryptolga@gmail.com
License: UNKNOWN
Keywords: coinzo exchange rest api bitcoin ethereum btc eth neo eos xrp hot try
Platform: UNKNOWN
Classifier: Development Status :: 4 - Beta
Classifier: Environment :: Console
Classifier: Intended Audience :: Developers
Classifier: License :: OSI Approved :: MIT License
Classifier: Natural Language :: English
Classifier: Operating System :: OS Independent
Classifier: Programming Language :: Python :: 3.6
Classifier: Programming Language :: Python :: 3.7
Classifier: Topic :: Software Development :: Libraries :: Python Modules
Requires-Python: >=3.6
Requires-Dist: requests
